{
  "$schema": "https://developer.microsoft.com/json-schemas/fabric/item/report/definition/visualContainer/1.5.0/schema.json",
  "name": "5822f8f54ea50e851219",
  "position": {
    "x": 609.6089385474861,
    "y": 184.13407821229052,
    "z": 6000,
    "height": 476.42458100558662,
    "width": 629.27374301675979,
    "tabOrder": 6000
  },
  "visual": {
    "visualType": "lineClusteredColumnComboChart",
    "query": {
      "queryState": {
        "Category": {
          "projections": [
            {
              "field": {
                "Column": {
                  "Expression": {
                    "SourceRef": {
                      "Entity": "fMain"
                    }
                  },
                  "Property": "Anomes"
                }
              },
              "queryRef": "fMain.Anomes",
              "nativeQueryRef": "Period",
              "active": true,
              "displayName": "Period"
            }
          ],
          "fieldParameters": [
            {
              "parameterExpr": {
                "Column": {
                  "Expression": {
                    "SourceRef": {
                      "Entity": "pEixo"
                    }
                  },
                  "Property": "pEixo"
                }
              },
              "index": 0,
              "length": 1
            }
          ]
        },
        "Y": {
          "projections": [
            {
              "field": {
                "Measure": {
                  "Expression": {
                    "SourceRef": {
                      "Entity": "Medidas"
                    }
                  },
                  "Property": "Kpi 0"
                }
              },
              "queryRef": "Medidas.Kpi 0",
              "nativeQueryRef": "Kpi 0",
              "displayName": "Kpi 0"
            }
          ],
          "fieldParameters": [
            {
              "parameterExpr": {
                "Column": {
                  "Expression": {
                    "SourceRef": {
                      "Entity": "pColuna"
                    }
                  },
                  "Property": "pColuna"
                }
              },
              "index": 0,
              "length": 1
            }
          ]
        },
        "Y2": {
          "projections": [
            {
              "field": {
                "Measure": {
                  "Expression": {
                    "SourceRef": {
                      "Entity": "Medidas"
                    }
                  },
                  "Property": "Kpi 0"
                }
              },
              "queryRef": "Medidas.Kpi 0",
              "nativeQueryRef": "Kpi 0",
              "displayName": "Kpi 0"
            }
          ],
          "fieldParameters": [
            {
              "parameterExpr": {
                "Column": {
                  "Expression": {
                    "SourceRef": {
                      "Entity": "pLinha"
                    }
                  },
                  "Property": "pLinha"
                }
              },
              "index": 0,
              "length": 1
            }
          ]
        }
      },
      "sortDefinition": {
        "sort": [
          {
            "field": {
              "Measure": {
                "Expression": {
                  "SourceRef": {
                    "Entity": "Medidas"
                  }
                },
                "Property": "Kpi 0"
              }
            },
            "direction": "Descending"
          }
        ],
        "isDefaultSort": true
      }
    },
    "drillFilterOtherVisuals": true
  }
}